cognitivefactory/features_maximization_metric/__init__.py
cognitivefactory/features_maximization_metric/fmc.py
cognitivefactory/features_maximization_metric/py.typed
cognitivefactory_features_maximization_metric-1.0.0.dist-info/WHEEL
cognitivefactory_features_maximization_metric-1.0.0.dist-info/METADATA
cognitivefactory_features_maximization_metric-1.0.0.dist-info/licenses/LICENSE.md
cognitivefactory_features_maximization_metric-1.0.0.dist-info/RECORD
