Metadata-Version: 2.1
Name: cognitivefactory-features-maximization-metric
Version: 1.0.0
Summary: Implementation of Features Maximization Metric, an unbiased metric aimed at estimate the quality of an unsupervised classification.
License: CECILL-C
Keywords: python,metrics,feature selection,features maximization
Author-email: Erwan Schild <erwan.schild@e-i.com>
Requires-Python: >=3.8
Classifier: Development Status :: 5 - Production/Stable
Classifier: Intended Audience :: Developers
Classifier: Programming Language :: Python
Classifier: Programming Language :: Python :: 3
Classifier: Programming Language :: Python :: 3 :: Only
Classifier: Programming Language :: Python :: 3.10
Classifier: Programming Language :: Python :: 3.11
Classifier: Programming Language :: Python :: 3.8
Classifier: Programming Language :: Python :: 3.9
Classifier: Topic :: Documentation
Classifier: Topic :: Software Development
Classifier: Topic :: Software Development :: Documentation
Classifier: Topic :: Utilities
Classifier: Typing :: Typed
Requires-Dist: numpy>=1.22.2
Requires-Dist: scikit-learn>=0.24.1
Requires-Dist: scipy>=1.7.3
Project-URL: Changelog, https://cognitivefactory.github.io/features-maximization-metric/changelog
Project-URL: Discussions, https://github.com/cognitivefactory/features-maximization-metric/discussions
Project-URL: Documentation, https://cognitivefactory.github.io/features-maximization-metric
Project-URL: Homepage, https://cognitivefactory.github.io/features-maximization-metric
Project-URL: Issues, https://github.com/cognitivefactory/features-maximization-metric/issues
Project-URL: Repository, https://github.com/cognitivefactory/features-maximization-metric
